setup.py
hellolibsssss/__init__.py
hellolibsssss/liruiqin.py
hellolibsssss.egg-info/PKG-INFO
hellolibsssss.egg-info/SOURCES.txt
hellolibsssss.egg-info/dependency_links.txt
hellolibsssss.egg-info/top_level.txt