Metadata-Version: 2.1
Name: hellolibsssss
Version: 0.0.1
Summary: yigeyonglaiwandeku
Home-page: https://github.com/
Author: none
Author-email: 
License: UNKNOWN
Platform: UNKNOWN
Classifier: Programming Language :: Python :: 3
Classifier: License :: OSI Approved :: MIT License
Classifier: Operating System :: OS Independent
